{
  "session_1": {
    "listen": {
      "part1": [
        {
          "topic": "โทรศัพท์",
          "answer": true
        },
        {
          "topic": "ลูกสาว",
          "answer": true
        },
        {
          "topic": "โต๊ะ 3 ตัว ",
          "answer": false
        },
        {
          "topic": "ข้างบน",
          "answer": true
        },
        {
          "topic": "ไม่เป็นไร",
          "answer": false
        }
      ],
      "part2": [
        {
          "topic": ["A .    ชอบเก้าอี้", " B .   ชอบแมว", " C .   อาหารอร่อย "],
          "answer": "a"
        },
        {
          "topic": ["A .   7:15", "B .   8:10", " C .   9:30"],
          "answer": "b"
        },
        {
          "topic": ["A .   ลูกชาย ", " B .   ครู", " C .   พ่อและแม่"],
          "answer": "a"
        },
        {
          "topic": ["A .   เรากินข้าว", "B .   แม่ทำงาน", "C .   พ่อไปปักกิ่ง"],
          "answer": "c"
        },
        {
          "topic": [
            "A .   อากาศร้อน",
            "B .   เสื้อตัวใหญ่เกิน",
            "C .   นักเรียนหลายคน"
          ],
          "answer": "b"
        }
      ],
      "part3": {
        "choice": [
          "A .  อ่านอักษรจีน",
          "B .  แก้ว 4 ใบ",
          "C .  ลูกชายเป็นหมอ",
          "D .  เห็นโรงพยาบาลไหม",
          "E .  ซื้อทีวี",
          "F .  ชอบอ่านหนังสือ"
        ],
        "answer": ["a", "c", "e", "d", "b"]
      },
      "part4": [
        {
          "topic": [
            { "pinin": "hěn  piàoliang", "ch": "A .   很   漂亮" },
            { "pinin": " ài   hē  chá", "ch": " B .   爱  喝   茶" },
            { "pinin": "xǐhuan  zuò  fàn", "ch": "C . 喜欢   做   饭" }
          ],

          "answer": "a"
        },
        {
          "topic": [
            {
              "pinin": " érzi   de   xuésheng",
              "ch": "A .  儿子  的     学生"
            },
            { "pinin": "  érzi   de  lǎoshī", "ch": "B . 儿子  的   老师" },
            { "pinin": "érzi  de  tóngxué", "ch": "C .  儿子  的    同学" }
          ],
          "answer": "c"
        },
        {
          "topic": [
            { "pinin": "xià  ge  yuè", "ch": "A . 下  个   月" },
            { "pinin": "xià ge  xīngqī", "ch": "B . 下 个   星期" },
            {
              "pinin": "xīngqīsān",
              "ch": "C . 星期三"
            }
          ],
          "answer": "b"
        },
        {
          "topic": [
            { "pinin": "huǒchēzhàn", "ch": "A . 火车站" },
            { "pinin": " jiā   li", "ch": "B .   家  里" },
            {
              "pinin": "péngyou  jiā",
              "ch": "C .  朋友    家"
            }
          ],
          "answer": "c"
        },
        {
          "topic": [
            { "pinin": " kuài", "ch": "A .  10   块" },
            { "pinin": " kuài", "ch": "B .  12   块" },
            {
              "pinin": " kuài",
              "ch": "C .  14   块"
            }
          ],
          "answer": "b"
        }
      ]
    },
    "reading": {
      "part1": [
        {
          "topic": {
            "th": "ขอบคุณ",
            "pinin": "xièxie",
            "ch": "谢谢"
          },
          "answer": true
        },
        {
          "topic": {
            "th": "กินข้าว",
            "pinin": "gōngzuò",
            "ch": "工作"
          },
          "answer": false
        },
        {
          "topic": {
            "th": "มาก",
            "pinin": "duō",
            "ch": "多"
          },
          "answer": true
        },
        {
          "topic": {
            "th": "เครื่องบิน",
            "pinin": "fēijī",
            "ch": "飞机"
          },
          "answer": true
        },
        {
          "topic": {
            "th": "ฟัง",
            "pinin": "xiě",
            "ch": "写"
          },
          "answer": false
        }
      ],
      "part2": {
        "topic": [
          {
            "pinin": "Wǒ  kāi  chē  huí  jiā.",
            "ch": " 我   开    车   回  家。 "
          },
          {
            "pinin": "Tā  zài   kàn  diànshì .",
            "ch": "他   在   看     电视 。"
          },
          {
            "pinin": "Jīntiān  tài  lěng  le,   yǒu  rè  shuǐ  ma?",
            "ch": " 今天  太    冷   了，有   热   水    吗 ？"
          },
          {
            "pinin": "Nǐ  de  diànhuà  shì  duōshǎo ?",
            "ch": " 你  的    电话     是      多少  ？"
          },
          {
            "pinin": "Zhè  shì  shéi  de  bēizi ?",
            "ch": "这    是    谁   的  杯子  ？"
          }
        ],
        "choice": [
          "A .  ขับรถ",
          "B .  อากาศหนาว",
          "C .  ขอเบอร์โทร",
          "D .  ดูทีวี",
          "E .  แก้วน้ำของใคร",
          "F .  กินผลไม้"
        ],
        "answer": ["a", "d", "b", "c", "e"]
      },
      "part3": {
        "topic": [
          {
            "pinin": "Nǐ  shénme  shíhòu  lái  Zhōngguó ?",
            "ch": "你    什么      时候   来     中国 ？"
          },
          {
            "pinin": "Zhège   yīfu  zěnmeyàng ?",
            "ch": "这个   衣服     怎么样 ？"
          },
          {
            "pinin": "Nǐ  xiànzài  zài  nǎr ?",
            "ch": "你    现在    在  哪儿 ？"
          },
          {
            "pinin": "Nǐ  bàba  zuò  shénme  gōngzuò ?",
            "ch": " 你  爸爸  做      什么      工作 ？"
          },
          {
            "pinin": "Nǐ  qù  Běijīng  jǐ  tiān ?",
            "ch": "你  去    北京   几  天 ？"
          }
        ],
        "choice": [
          {
            "pinin": "Jiā   lǐ .",
            "ch": " A .   家  里 。"
          },
          {
            "pinin": "Yí  ge  xīngqī .",
            "ch": "B . 一  个   星期 。"
          },
          {
            "pinin": " Tā  shì  yīshēng .",
            "ch": "  C .  他  是    医生 。"
          },
          {
            "pinin": " yuè   rì .",
            "ch": "  D .  4  月  25  日 。"
          },
          {
            "pinin": " Tài  xiǎo   le .",
            "ch": "   E . 太   小    了 。 "
          },
          {
            "pinin": " Bù  xǐhuan .",
            "ch": "  F .  不    喜欢 。"
          }
        ],
        "answer": ["d", "e", "a", "c", "b"]
      },
      "part4": {
        "topic": [
          {
            "pinin": "Tā  bù  zài  jiā,    nǐ",
            "ch": "他  不   在  家，你",
            "pinin_end": " lái  hǎo  ma ?",
            "ch_end": "来   好   吗 ？"
          },
          {
            "pinin": "Tā   xiàwǔ",
            "ch": " 他    下午",
            "pinin_end": " wǒmen   chī  fàn .",
            "ch_end": "我们      吃   饭 。"
          },
          {
            "pinin": "Tiānqì  tài ",
            "ch": " 天气   太",
            "pinin_end": " le,    nǐ   hē  shuǐ  ma ?",
            "ch_end": "了，你  喝   水    吗 ？"
          },
          {
            "pinin": " Nǐ  shuìjiào  le  ma? ",
            "ch": "男：你    睡觉    了  吗 ？",
            "pinin_sec": "Méi  ne,  wǒ  zài",
            "ch_sec": "女：没    呢，我   在 ",
            "pinin_sec_end": " shū .",
            "ch_sec_end": "  书 。"
          },
          {
            "pinin": "Nàge  fàndiàn  zài   nǎr ?",
            "ch": "男：那个   饭店     在  哪儿 ？",

            "pinin_sec": "Xuéxiào",
            "ch_sec": "女：  学校  "
          }
        ],
        "choice": [
          {
            "pinin": " rè",
            "ch": "A . 热"
          },
          {
            "pinin": " qǐng",
            "ch": "B . 请"
          },
          {
            "pinin": "míngtiān",
            "ch": "C . 明天"
          },
          {
            "pinin": "dú",
            "ch": "D . 读"
          },
          {
            "pinin": "hòumiàn",
            "ch": "E .  后面"
          },
          {
            "pinin": "bù ",
            "ch": "F .  不"
          }
        ],
        "answer": ["c", "b", "a", "d", "e"]
      }
    }
  },
  "session_2":{
    "listen": {
      "part1": [
        {
          "topic": "ทำอาหาร",
          "answer": false
        },
        {
          "topic": "แมวและหมา",
          "answer": true
        },
        {
          "topic": "คนจีน",
          "answer": true
        },
        {
          "topic": "แก้วน้ำของฉัน",
          "answer": false
        },
        {
          "topic": "ขอบคุณมาก",
          "answer": false
        }
      ],
      "part2": [
        {
          "topic": ["A .   บนโต๊ะมีแก้วน้ำ", " B .   บนเก้าอี้มีแมว", " C .   ข้างในมีอะไร "],
          "answer": "a"
        },
        {
          "topic": ["A . แม่เป็นครู", "B .   ฉันเป็นนักเรียน", " C .  พ่อเป็นหมอ"],
          "answer": "c"
        },
        {
          "topic": ["A .  ซื้อคอมพิวเตอร์", " B .  อยากดูหนัง", " C .  ไปโรงเรียน"],
          "answer": "a"
        },
        {
          "topic": ["A .   ดีใจจัง", "B .  อากาศร้อนมาก", "C .  ฝนกำลังตก"],
          "answer": "b"
        },
        {
          "topic": [
            "A .   พ่ออ่านหนังสือ",
            "B .   เขาสวยมาก",
            "C .   ลูกชายหลับแล้ว"
          ],
          "answer": "b"
        }
      ],
      "part3": {
        "choice": [
          "A .  ทำอาหาร",
          "B .  ขับรถ",
          "C .  8:10",
          "D .  ลาก่อน แล้วเจอกัน",
          "E .  เรียนมหาวิทยาลัย",
          "F .  ชอบอ่านหนังสือ"
        ],
        "answer": ["b", "e", "c", "d", "a"]
      },
      "part4": [
        {
          "topic": [
            { "pinin": "nián", "ch": "A . 4   年" },
            { "pinin": " nián", "ch": " B .  6    年" },
            { "pinin": " nián", "ch": "C . 8   年" }
          ],

          "answer": "b"
        },
        {
          "topic": [
            {
              "pinin": "zuò   fēijī",
              "ch": "A . 坐   飞机"
            },
            { "pinin": "  zuò  huǒchē", "ch": "B . 坐     火车" },
            { "pinin": "kāi  chē", "ch": "C . 开   车" }
          ],
          "answer": "a"
        },
        {
          "topic": [
            { "pinin": " yǐzi  shang", "ch": "A .  椅子   上" },
            { "pinin": " zhuōzi   xia", "ch": "B . 桌子    下" },
            {
              "pinin": "diànshì  hòumiàn",
              "ch": "C . 电视      后面"
            }
          ],
          "answer": "b"
        },
        {
          "topic": [
            { "pinin": "bù  xiǎng  qù  yīyuàn", "ch": "A . 不   想     去    医院" },
            { "pinin": "bù  xiǎng  kàn  diànshì", "ch": "B .   不    想     看     电视" },
            {
              "pinin": "bù  xiǎng  huí  jiā",
              "ch": "C .  不    想     回    家"
            }
          ],
          "answer": "b"
        },
        {
          "topic": [
            { "pinin": " érzi    de  tóngxué", "ch": "A .  儿子  的    同学" },
            { "pinin": " māma  de  péngyou", "ch": "B .   妈妈   的     朋友" },
            {
              "pinin": "nǚ'ér  de  péngyou",
              "ch": "C .  女儿  的    朋友"
            }
          ],
          "answer": "c"
        }
      ]
    },
    "reading": {
      "part1": [
        {
          "topic": {
            "th": "ฟัง",
            "pinin": "tīng",
            "ch": "听"
          },
          "answer": true
        },
        {
          "topic": {
            "th": "สวย",
            "pinin": "piàoliang",
            "ch": "漂亮"
          },
          "answer": true
        },
        {
          "topic": {
            "th": "คุณผู้หญิง",
            "pinin": "xiānsheng",
            "ch": "先生"
          },
          "answer": false
        },
        {
          "topic": {
            "th": "ข้าว",
            "pinin": "shuǐ",
            "ch": "水"
          },
          "answer": false
        },
        {
          "topic": {
            "th": "ร้อน",
            "pinin": "lěng",
            "ch": "冷"
          },
          "answer": false
        }
      ],
      "part2": {
        "topic": [
          {
            "pinin": "Nàge    bēizi       kuài qián .",
            "ch": " 那个     杯子    5  块   钱 。 "
          },
          {
            "pinin": "Wǒ  xiǎng  xuéxí  kāi  chē.",
            "ch": "我     想     学习   开    车  。"
          },
          {
            "pinin": "Zhè  lǐmiàn   shì  shénme  dōngxi ?",
            "ch": "这    里面     是    什么     东西 ？"
          },
          {
            "pinin": "Cài  zài  zhuōzi  shang .",
            "ch": " 菜    在    桌子     上 。"
          },
          {
            "pinin": "Tā  shì  wǒ  bàba  de  xuéshēng .",
            "ch": "他  是   我  爸爸  的     学生 。"
          }
        ],
        "choice": [
          "A .  อะไรอยู่ในนี้",
          "B .  ราคาแก้วน้ำ",
          "C .  อาหารอยู่บนโต๊ะ",
          "D .  เรียนขับรถ",
          "E .  นักเรียนของพ่อ",
          "F .  กินผลไม้"
        ],
        "answer": ["b", "d", "a", "c", "e"]
      },
      "part3": {
        "topic": [
          {
            "pinin": "Nǐmen shénme shíhòu huí lai ?",
            "ch": "你们    什么    时候   回  来 ？"
          },
          {
            "pinin": "Zuótiān  tiānqì  zěnmeyàng ? ",
            "ch": "昨天    天气      怎么样 ？"
          },
          {
            "pinin": "Nàge  rén  shì  shéi ?",
            "ch": "那个  人   是   谁 ？"
          },
          {
            "pinin": "Wǒ  de  gǒu  qù  nǎ'r    le ?",
            "ch": " 我  的   狗   去  哪儿  了 ？"
          },
          {
            "pinin": "Nǐmen  xuéxiào  yǒu  duōshǎo  lǎoshī ?",
            "ch": "你们      学校     有      多少     老师 ？"
          }
        ],
        "choice": [
          {
            "pinin": "Wǒ  de  tóngxué .",
            "ch": " A . 我   的    同学 。"
          },
          {
            "pinin": "ge ．",
            "ch": "B . 95  个。"
          },
          {
            "pinin": "Yǐzi  xiàmiàn .",
            "ch": "  C .  椅子   下面 。"
          },
          {
            "pinin": "yuè    rì .",
            "ch": "  D . 1  月  3  日 。"
          },
          {
            "pinin": "Xiàyǔ  le . ",
            "ch": "   E . 下雨   了 。"
          },
          {
            "pinin": "Bù  xǐhuan .",
            "ch": "  F . 不    喜欢 。"
          }
        ],
        "answer": ["d", "e", "a", "c", "b"]
      },
      "part4": {
        "topic": [
          {
            "pinin": "Tā",
            "ch": "他",
            "pinin_end": " xiě  bù  shǎo  Hànzì .",
            "ch_end": "写  不   少     汉字 。"
          },
          {
            "pinin": "Wáng lǎoshī  jīnnián",
            "ch": "王    老师    今年    50",
            "pinin_end": "le .",
            "ch_end": "了 。"
          },
          {
            "pinin": "Nǐ  jiào  shénme",
            "ch": "你  叫      什么  ",
            "pinin_end": "",
            "ch_end": " ？"
          },
          {
            "pinin": "Nǐ  zuótiān  zěnme  méi  qù  kàn",
            "ch": "男：你   昨天      怎么    没   去   看 ",
            "pinin_end": "",
            "ch_end": "你 ！",
            "pinin_sec": "Zuótiān  wǒ  qù  kàn  yīshēng  le ．",
            "ch_sec": "女：   昨天    我  去   看     医生    了。"
          },
          {
            "pinin": "Wǒ  hěn  xǐhuan  zhège  yīfu,",
            "ch": "男：我   很    喜欢     这个  衣服，",
            "pinin_end": "nǐ ! ",
            "ch_end": "你 ！",
            "pinin_sec": "Bú  kèqi .",
            "ch_sec": "女：不   客气 。"
          }
        ],
        "choice": [
          {
            "pinin": "diànyǐng",
            "ch": "A . 电影"
          },
          {
            "pinin": " míngzi",
            "ch": "B . 名字"
          },
          {
            "pinin": " suì",
            "ch": "C . 岁"
          },
          {
            "pinin": "xièxie",
            "ch": "D . 谢谢 "
          },
          {
            "pinin": "huì",
            "ch": "E . 会"
          },
          {
            "pinin": "bù",
            "ch": "F .  不"
          }
        ],
        "answer": ["e", "c", "b", "a", "d"]
      }
    }

  }
}
